<SceneText>
  <Speakers>
    <Section>Speaker</Section>
    <Entry>
      <JapaneseText>ハロルド</JapaneseText>
      <EnglishText/>
      <Notes/>
      <Id>22</Id>
      <Status>To Do</Status>
    </Entry>
    <Entry>
      <JapaneseText>リフィル</JapaneseText>
      <EnglishText/>
      <Notes/>
      <Id>27</Id>
      <Status>To Do</Status>
    </Entry>
    <Entry>
      <JapaneseText>キール</JapaneseText>
      <EnglishText/>
      <Notes/>
      <Id>17</Id>
      <Status>To Do</Status>
    </Entry>
    <Entry>
      <JapaneseText>ルビア</JapaneseText>
      <EnglishText/>
      <Notes/>
      <Id>46</Id>
      <Status>To Do</Status>
    </Entry>
    <Entry>
      <JapaneseText>コレット</JapaneseText>
      <EnglishText/>
      <Notes/>
      <Id>25</Id>
      <Status>To Do</Status>
    </Entry>
  </Speakers>
  <Strings>
    <Section>Main Text</Section>
    <Entry>
      <JapaneseText>はいはい、なーんか集まってるわねぇ。
いいわよ〜、質問があるなら
挙手にてどうぞ</JapaneseText>
      <EnglishText/>
      <Notes/>
      <SpeakerId>22</SpeakerId>
      <Id>0</Id>
      <Status>To Do</Status>
    </Entry>
    <Entry>
      <JapaneseText>はい。
ではまず私から</JapaneseText>
      <EnglishText/>
      <Notes/>
      <SpeakerId>27</SpeakerId>
      <Id>1</Id>
      <Status>To Do</Status>
    </Entry>
    <Entry>
      <JapaneseText>なぜ男の名前を名乗っているの？</JapaneseText>
      <EnglishText/>
      <Notes/>
      <SpeakerId>27</SpeakerId>
      <Id>2</Id>
      <Status>To Do</Status>
    </Entry>
    <Entry>
      <JapaneseText>面白いからよ。
男と誤解されてね。
以上！　はい、次！</JapaneseText>
      <EnglishText/>
      <Notes/>
      <SpeakerId>22</SpeakerId>
      <Id>3</Id>
      <Status>To Do</Status>
    </Entry>
    <Entry>
      <JapaneseText>はい、次はぼくだ</JapaneseText>
      <EnglishText/>
      <Notes/>
      <SpeakerId>17</SpeakerId>
      <Id>4</Id>
      <Status>To Do</Status>
    </Entry>
    <Entry>
      <JapaneseText>あんたの科学的業績は結構なものだが、
なぜ以前のギルドでは疎まれてた？</JapaneseText>
      <EnglishText/>
      <Notes/>
      <SpeakerId>17</SpeakerId>
      <Id>5</Id>
      <Status>To Do</Status>
    </Entry>
    <Entry>
      <JapaneseText>さあ？　私の事、ギルドの長が
嫌ってたからじゃない？</JapaneseText>
      <EnglishText/>
      <Notes/>
      <SpeakerId>22</SpeakerId>
      <Id>6</Id>
      <Status>To Do</Status>
    </Entry>
    <Entry>
      <JapaneseText>はい、次、あたし！
なぜギルドで働くの？</JapaneseText>
      <EnglishText/>
      <Notes/>
      <SpeakerId>46</SpeakerId>
      <Id>7</Id>
      <Status>To Do</Status>
    </Entry>
    <Entry>
      <JapaneseText>有名な学者さんだったら、
ギルドで働かず、もっと別の所で
働けばいいんじゃないかしら？</JapaneseText>
      <EnglishText/>
      <Notes/>
      <SpeakerId>46</SpeakerId>
      <Id>8</Id>
      <Status>To Do</Status>
    </Entry>
    <Entry>
      <JapaneseText>軍の研究施設で働いた事あったけど、
好き勝手しちゃあ怒られるのよね。
そんなの面白くないじゃない</JapaneseText>
      <EnglishText/>
      <Notes/>
      <SpeakerId>22</SpeakerId>
      <Id>9</Id>
      <Status>To Do</Status>
    </Entry>
    <Entry>
      <JapaneseText>ほい、次</JapaneseText>
      <EnglishText/>
      <Notes/>
      <SpeakerId>22</SpeakerId>
      <Id>10</Id>
      <Status>To Do</Status>
    </Entry>
    <Entry>
      <JapaneseText>はい、私もいいかなぁ？</JapaneseText>
      <EnglishText/>
      <Notes/>
      <SpeakerId>25</SpeakerId>
      <Id>11</Id>
      <Status>To Do</Status>
    </Entry>
    <Entry>
      <JapaneseText>犬派？　猫派？</JapaneseText>
      <EnglishText/>
      <Notes/>
      <SpeakerId>25</SpeakerId>
      <Id>12</Id>
      <Status>To Do</Status>
    </Entry>
    <Entry>
      <JapaneseText>あら、二択じゃないと駄目？
好きな生き物は研究対象全般
なんだけどね</JapaneseText>
      <EnglishText/>
      <Notes/>
      <SpeakerId>22</SpeakerId>
      <Id>13</Id>
      <Status>To Do</Status>
    </Entry>
    <Entry>
      <JapaneseText>世界樹をどう思う？</JapaneseText>
      <EnglishText/>
      <Notes>Choice 1</Notes>
      <Id>14</Id>
      <Status>To Do</Status>
    </Entry>
    <Entry>
      <JapaneseText>やる気はあるのか？</JapaneseText>
      <EnglishText/>
      <Notes>Choice 2</Notes>
      <Id>15</Id>
      <Status>To Do</Status>
    </Entry>
    <Entry>
      <JapaneseText>どうとも思わないわね。
ま、必要な人には必要なんでしょう</JapaneseText>
      <EnglishText/>
      <Notes/>
      <SpeakerId>22</SpeakerId>
      <Id>16</Id>
      <Status>To Do</Status>
    </Entry>
    <Entry>
      <JapaneseText>具体性に欠く質問ね</JapaneseText>
      <EnglishText/>
      <Notes>Previous Choice 2 leads here</Notes>
      <SpeakerId>22</SpeakerId>
      <Id>17</Id>
      <Status>To Do</Status>
    </Entry>
    <Entry>
      <JapaneseText>何に対してなのか、そして
「ある」「なし」の二元論的で
答えていいものかしら</JapaneseText>
      <EnglishText/>
      <Notes/>
      <SpeakerId>22</SpeakerId>
      <Id>18</Id>
      <Status>To Do</Status>
    </Entry>
    <Entry>
      <JapaneseText>もっと条件を限定して
もらいたいものね</JapaneseText>
      <EnglishText/>
      <Notes/>
      <SpeakerId>22</SpeakerId>
      <Id>19</Id>
      <Status>To Do</Status>
    </Entry>
    <Entry>
      <JapaneseText>他に質問は？</JapaneseText>
      <EnglishText/>
      <Notes/>
      <SpeakerId>22</SpeakerId>
      <Id>20</Id>
      <Status>To Do</Status>
    </Entry>
    <Entry>
      <JapaneseText>ありゃりゃ、
まだまだあるみたいね〜…</JapaneseText>
      <EnglishText/>
      <Notes/>
      <SpeakerId>22</SpeakerId>
      <Id>21</Id>
      <Status>To Do</Status>
    </Entry>
  </Strings>
  <Strings>
    <Section>Unreferenced</Section>
  </Strings>
</SceneText>
