<SceneText>
  <Speakers>
    <Section>Speaker</Section>
    <Entry>
      <JapaneseText>ハロルド</JapaneseText>
      <EnglishText/>
      <Notes/>
      <Id>22</Id>
      <Status>To Do</Status>
    </Entry>
    <Entry>
      <JapaneseText>カイル</JapaneseText>
      <EnglishText/>
      <Notes/>
      <Id>19</Id>
      <Status>To Do</Status>
    </Entry>
    <Entry>
      <JapaneseText>リアラ</JapaneseText>
      <EnglishText/>
      <Notes/>
      <Id>20</Id>
      <Status>To Do</Status>
    </Entry>
  </Speakers>
  <Strings>
    <Section>Main Text</Section>
    <Entry>
      <JapaneseText>さ〜て、あんた達二人には
しっかり働いてもらわないとねえ</JapaneseText>
      <EnglishText/>
      <Notes/>
      <SpeakerId>22</SpeakerId>
      <Id>0</Id>
      <Status>To Do</Status>
    </Entry>
    <Entry>
      <JapaneseText>うん！　オレ、頑張る！</JapaneseText>
      <EnglishText/>
      <Notes/>
      <SpeakerId>19</SpeakerId>
      <Id>1</Id>
      <Status>To Do</Status>
    </Entry>
    <Entry>
      <JapaneseText>いい子ね。
ちょっと思考能力の欠如傾向が
見られるけど</JapaneseText>
      <EnglishText/>
      <Notes/>
      <SpeakerId>22</SpeakerId>
      <Id>2</Id>
      <Status>To Do</Status>
    </Entry>
    <Entry>
      <JapaneseText>でしょ！
よくいい子って言われるんだ</JapaneseText>
      <EnglishText/>
      <Notes/>
      <SpeakerId>19</SpeakerId>
      <Id>3</Id>
      <Status>To Do</Status>
    </Entry>
    <Entry>
      <JapaneseText>「馬鹿」って言われた事は
スルーなのね…</JapaneseText>
      <EnglishText/>
      <Notes/>
      <SpeakerId>20</SpeakerId>
      <Id>4</Id>
      <Status>To Do</Status>
    </Entry>
  </Strings>
  <Strings>
    <Section>Unreferenced</Section>
  </Strings>
</SceneText>
