<SceneText>
  <Speakers>
    <Section>Speaker</Section>
    <Entry>
      <PointerOffset/>
      <JapaneseText>ルビア</JapaneseText>
      <EnglishText/>
      <Notes/>
      <Id>46</Id>
      <Status>To Do</Status>
    </Entry>
    <Entry>
      <PointerOffset/>
      <JapaneseText>ヴェイグ</JapaneseText>
      <EnglishText/>
      <Notes/>
      <Id>32</Id>
      <Status>To Do</Status>
    </Entry>
    <Entry>
      <PointerOffset/>
      <JapaneseText>ゼロス</JapaneseText>
      <EnglishText/>
      <Notes/>
      <Id>29</Id>
      <Status>To Do</Status>
    </Entry>
  </Speakers>
  <Strings>
    <Section>Main Text</Section>
    <Entry>
      <PointerOffset/>
      <JapaneseText>ねえ、ヴェイグさん。
クレアさんってステキな方ですね</JapaneseText>
      <EnglishText/>
      <Notes/>
      <SpeakerId>46</SpeakerId>
      <Id>0</Id>
      <Status>To Do</Status>
    </Entry>
    <Entry>
      <PointerOffset/>
      <JapaneseText>…そうかもな</JapaneseText>
      <EnglishText/>
      <Notes/>
      <SpeakerId>32</SpeakerId>
      <Id>1</Id>
      <Status>To Do</Status>
    </Entry>
    <Entry>
      <PointerOffset/>
      <JapaneseText>あたし、クレアさんみたいな
大人になりたいなぁ</JapaneseText>
      <EnglishText/>
      <Notes/>
      <SpeakerId>46</SpeakerId>
      <Id>2</Id>
      <Status>To Do</Status>
    </Entry>
    <Entry>
      <PointerOffset/>
      <JapaneseText>といっても二つしか歳が
変わらないんですよね。
あたしあんな風になれるかしら</JapaneseText>
      <EnglishText/>
      <Notes/>
      <SpeakerId>46</SpeakerId>
      <Id>3</Id>
      <Status>To Do</Status>
    </Entry>
    <Entry>
      <PointerOffset/>
      <JapaneseText>ヴェイグみたいな
ムッツリ野郎に付きまとわれちまうかも
しれね〜ぜ？　げひゃひゃひゃひゃ</JapaneseText>
      <EnglishText/>
      <Notes/>
      <SpeakerId>29</SpeakerId>
      <Id>4</Id>
      <Status>To Do</Status>
    </Entry>
    <Entry>
      <PointerOffset/>
      <JapaneseText>………</JapaneseText>
      <EnglishText/>
      <Notes/>
      <SpeakerId>32</SpeakerId>
      <Id>5</Id>
      <Status>To Do</Status>
    </Entry>
    <Entry>
      <PointerOffset/>
      <JapaneseText>おいおい、ジョークだろ〜？
そんな怒んじゃねぇよなぁ</JapaneseText>
      <EnglishText/>
      <Notes/>
      <SpeakerId>29</SpeakerId>
      <Id>6</Id>
      <Status>To Do</Status>
    </Entry>
    <Entry>
      <PointerOffset/>
      <JapaneseText>ヴェイグさん、
そんなに怖い顔しなくても…</JapaneseText>
      <EnglishText/>
      <Notes/>
      <SpeakerId>46</SpeakerId>
      <Id>7</Id>
      <Status>To Do</Status>
    </Entry>
    <Entry>
      <PointerOffset/>
      <JapaneseText>いや、別に怒ったわけじゃ
ないんだが…</JapaneseText>
      <EnglishText/>
      <Notes/>
      <SpeakerId>32</SpeakerId>
      <Id>8</Id>
      <Status>To Do</Status>
    </Entry>
    <Entry>
      <PointerOffset/>
      <JapaneseText>そんなに怖いか？
オレの顔…</JapaneseText>
      <EnglishText/>
      <Notes/>
      <SpeakerId>32</SpeakerId>
      <Id>9</Id>
      <Status>To Do</Status>
    </Entry>
    <Entry>
      <PointerOffset/>
      <JapaneseText>………</JapaneseText>
      <EnglishText/>
      <Notes/>
      <SpeakerId>46</SpeakerId>
      <Id>10</Id>
      <Status>To Do</Status>
    </Entry>
  </Strings>
  <Strings>
    <Section>Unreferenced</Section>
  </Strings>
</SceneText>
