<SceneText>
  <Speakers>
    <Section>Speaker</Section>
    <Entry>
      <JapaneseText>イリア</JapaneseText>
      <EnglishText/>
      <Notes/>
      <Id>48</Id>
      <Status>To Do</Status>
    </Entry>
    <Entry>
      <JapaneseText>ルカ</JapaneseText>
      <EnglishText/>
      <Notes/>
      <Id>47</Id>
      <Status>To Do</Status>
    </Entry>
    <Entry>
      <JapaneseText>ルビア</JapaneseText>
      <EnglishText/>
      <Notes/>
      <Id>46</Id>
      <Status>To Do</Status>
    </Entry>
  </Speakers>
  <Strings>
    <Section>Main Text</Section>
    <Entry>
      <JapaneseText>ね、ルカ〜。
なんであたし船に乗ってんの〜…</JapaneseText>
      <EnglishText/>
      <Notes/>
      <SpeakerId>48</SpeakerId>
      <Id>0</Id>
      <Status>To Do</Status>
    </Entry>
    <Entry>
      <JapaneseText>…いきなり不機嫌全開だね。
ひょっとして気分悪いの？</JapaneseText>
      <EnglishText/>
      <Notes/>
      <SpeakerId>47</SpeakerId>
      <Id>1</Id>
      <Status>To Do</Status>
    </Entry>
    <Entry>
      <JapaneseText>あったぼうよぉ！！
なんでみんな船酔いしないの？
変なんじゃない？</JapaneseText>
      <EnglishText/>
      <Notes/>
      <SpeakerId>48</SpeakerId>
      <Id>2</Id>
      <Status>To Do</Status>
    </Entry>
    <Entry>
      <JapaneseText>そ、そうかな？
僕は船平気だけど…</JapaneseText>
      <EnglishText/>
      <Notes/>
      <SpeakerId>47</SpeakerId>
      <Id>3</Id>
      <Status>To Do</Status>
    </Entry>
    <Entry>
      <JapaneseText>なんかズルをしてんでしょ？
ね、いくらぐらいお金積んだの？</JapaneseText>
      <EnglishText/>
      <Notes/>
      <SpeakerId>48</SpeakerId>
      <Id>4</Id>
      <Status>To Do</Status>
    </Entry>
    <Entry>
      <JapaneseText>そ、そんな事してないよ！
意味わかんないし。
何？　その黒い感じ…</JapaneseText>
      <EnglishText/>
      <Notes/>
      <SpeakerId>47</SpeakerId>
      <Id>5</Id>
      <Status>To Do</Status>
    </Entry>
    <Entry>
      <JapaneseText>んがぁぁああ、吐きそう！
今なら全力で吐けそう！
いい？　ルカにいい？</JapaneseText>
      <EnglishText/>
      <Notes/>
      <SpeakerId>48</SpeakerId>
      <Id>6</Id>
      <Status>To Do</Status>
    </Entry>
    <Entry>
      <JapaneseText>わ、わ、わ！　止めてよ！
うわぁぁあ〜〜〜</JapaneseText>
      <EnglishText/>
      <Notes/>
      <SpeakerId>47</SpeakerId>
      <Id>7</Id>
      <Status>To Do</Status>
    </Entry>
    <Entry>
      <JapaneseText>………</JapaneseText>
      <EnglishText/>
      <Notes/>
      <SpeakerId>48</SpeakerId>
      <Id>8</Id>
      <Status>To Do</Status>
    </Entry>
    <Entry>
      <JapaneseText>またルカをからかって…。
ほ〜んと仲がいいのね</JapaneseText>
      <EnglishText/>
      <Notes/>
      <SpeakerId>46</SpeakerId>
      <Id>9</Id>
      <Status>To Do</Status>
    </Entry>
    <Entry>
      <JapaneseText>おほほほ、あなたとカイウスほどじゃ
ござんせん事ですのよ〜？</JapaneseText>
      <EnglishText/>
      <Notes/>
      <SpeakerId>48</SpeakerId>
      <Id>10</Id>
      <Status>To Do</Status>
    </Entry>
    <Entry>
      <JapaneseText>カイウスの事は
関係ないじゃない！</JapaneseText>
      <EnglishText/>
      <Notes/>
      <SpeakerId>46</SpeakerId>
      <Id>11</Id>
      <Status>To Do</Status>
    </Entry>
    <Entry>
      <JapaneseText>うっほ〜〜、怒った〜。
逃っげろ〜</JapaneseText>
      <EnglishText/>
      <Notes/>
      <SpeakerId>48</SpeakerId>
      <Id>12</Id>
      <Status>To Do</Status>
    </Entry>
    <Entry>
      <JapaneseText>………</JapaneseText>
      <EnglishText/>
      <Notes/>
      <SpeakerId>46</SpeakerId>
      <Id>13</Id>
      <Status>To Do</Status>
    </Entry>
    <Entry>
      <JapaneseText>ふ〜ん…。
ルカと仲良しって事は
否定しなかったわね…</JapaneseText>
      <EnglishText/>
      <Notes/>
      <SpeakerId>46</SpeakerId>
      <Id>14</Id>
      <Status>To Do</Status>
    </Entry>
  </Strings>
  <Strings>
    <Section>Unreferenced</Section>
  </Strings>
</SceneText>
