<SceneText>
  <Speakers>
    <Section>Speaker</Section>
    <Entry>
      <JapaneseText>ミント</JapaneseText>
      <EnglishText/>
      <Notes/>
      <Id>4</Id>
      <Status>To Do</Status>
    </Entry>
  </Speakers>
  <Strings>
    <Section>Main Text</Section>
    <Entry>
      <JapaneseText>こんにちは。
ご挨拶がまだでしたね？</JapaneseText>
      <EnglishText/>
      <Notes/>
      <SpeakerId>4</SpeakerId>
      <Id>0</Id>
      <Status>To Do</Status>
    </Entry>
    <Entry>
      <JapaneseText>私はミント・アドネードです。
ロゼット村ではギルドで、人々の
助けになるよう働いていました</JapaneseText>
      <EnglishText/>
      <Notes/>
      <SpeakerId>4</SpeakerId>
      <Id>1</Id>
      <Status>To Do</Status>
    </Entry>
    <Entry>
      <JapaneseText>まだまだ力不足ですが、
今後ともよろしくお願いします</JapaneseText>
      <EnglishText/>
      <Notes/>
      <SpeakerId>4</SpeakerId>
      <Id>2</Id>
      <Status>To Do</Status>
    </Entry>
  </Strings>
  <Strings>
    <Section>Unreferenced</Section>
  </Strings>
</SceneText>
