<SceneText>
  <Speakers>
    <Section>Speaker</Section>
    <Entry>
      <JapaneseText>ニアタ</JapaneseText>
      <EnglishText/>
      <Notes/>
      <Id>54</Id>
      <Status>To Do</Status>
    </Entry>
  </Speakers>
  <Strings>
    <Section>Main Text</Section>
    <Entry>
      <JapaneseText>ディセンダー、叫べ。
ヤツの名を</JapaneseText>
      <EnglishText/>
      <Notes/>
      <SpeakerId>54</SpeakerId>
      <Id>1</Id>
      <Status>To Do</Status>
    </Entry>
    <Entry>
      <JapaneseText>よいか、この世に「無」などないのだ！
奴がどんなに立ち止まろうと
その心を突き動かしてやれ！</JapaneseText>
      <EnglishText/>
      <Notes/>
      <SpeakerId>54</SpeakerId>
      <Id>2</Id>
      <Status>To Do</Status>
    </Entry>
    <Entry>
      <JapaneseText>そなたの戦いは、
奴に自分自身を思い出させ、
自分自身を受け入れさせる事だ！</JapaneseText>
      <EnglishText/>
      <Notes/>
      <SpeakerId>54</SpeakerId>
      <Id>3</Id>
      <Status>To Do</Status>
    </Entry>
  </Strings>
  <Strings>
    <Section>Unreferenced</Section>
    <Entry>
      <JapaneseText>evobj_033</JapaneseText>
      <EnglishText/>
      <Notes/>
      <Id>0</Id>
      <Status>To Do</Status>
    </Entry>
  </Strings>
</SceneText>
