<SceneText>
  <Speakers>
    <Section>Speaker</Section>
    <Entry>
      <PointerOffset/>
      <JapaneseText>ゼロス</JapaneseText>
      <EnglishText/>
      <Notes/>
      <Id>29</Id>
      <Status>To Do</Status>
    </Entry>
    <Entry>
      <PointerOffset/>
      <JapaneseText>ジェイド</JapaneseText>
      <EnglishText/>
      <Notes/>
      <Id>42</Id>
      <Status>To Do</Status>
    </Entry>
  </Speakers>
  <Strings>
    <Section>Main Text</Section>
    <Entry>
      <PointerOffset/>
      <JapaneseText>さあて、そんじゃサクッと
連れ戻しちゃおうぜ〜</JapaneseText>
      <EnglishText/>
      <Notes/>
      <SpeakerId>29</SpeakerId>
      <Id>0</Id>
      <Status>To Do</Status>
    </Entry>
    <Entry>
      <PointerOffset/>
      <JapaneseText>ですが、あの二人。
自分の意思でここに来たんでしたら
「負」の影響の可能性が高いかと思われます</JapaneseText>
      <EnglishText/>
      <Notes/>
      <SpeakerId>42</SpeakerId>
      <Id>1</Id>
      <Status>To Do</Status>
    </Entry>
    <Entry>
      <PointerOffset/>
      <JapaneseText>そう簡単に戻ってもらえるとも
思えませんが</JapaneseText>
      <EnglishText/>
      <Notes/>
      <SpeakerId>42</SpeakerId>
      <Id>2</Id>
      <Status>To Do</Status>
    </Entry>
    <Entry>
      <PointerOffset/>
      <JapaneseText>まあ、そういう場合はすこ〜しだけ
痛い目にあってもらわねーとなあ</JapaneseText>
      <EnglishText/>
      <Notes/>
      <SpeakerId>29</SpeakerId>
      <Id>3</Id>
      <Status>To Do</Status>
    </Entry>
    <Entry>
      <PointerOffset/>
      <JapaneseText>イリアちゃんみたいな女の子とルカみたいな
か弱き乙女、…じゃねえナヨナヨ相手に
暴れんのは心痛むけどな</JapaneseText>
      <EnglishText/>
      <Notes/>
      <SpeakerId>29</SpeakerId>
      <Id>4</Id>
      <Status>To Do</Status>
    </Entry>
    <Entry>
      <PointerOffset/>
      <JapaneseText>それは同感です。
ただ、イリアはあなたの事を
あまり好きではないようですからね</JapaneseText>
      <EnglishText/>
      <Notes/>
      <SpeakerId>42</SpeakerId>
      <Id>5</Id>
      <Status>To Do</Status>
    </Entry>
    <Entry>
      <PointerOffset/>
      <JapaneseText>意趣返し的な意味合いが
あなたの行動に込められていないか
どうかが気がかりです</JapaneseText>
      <EnglishText/>
      <Notes/>
      <SpeakerId>42</SpeakerId>
      <Id>6</Id>
      <Status>To Do</Status>
    </Entry>
    <Entry>
      <PointerOffset/>
      <JapaneseText>ってか、イリアちゃんに好かれてないのは
俺さまだけじゃないじゃん。
あんたもそうだぜ、ジェイド</JapaneseText>
      <EnglishText/>
      <Notes/>
      <SpeakerId>29</SpeakerId>
      <Id>7</Id>
      <Status>To Do</Status>
    </Entry>
    <Entry>
      <PointerOffset/>
      <JapaneseText>そういえばそうでしたかね</JapaneseText>
      <EnglishText/>
      <Notes/>
      <SpeakerId>42</SpeakerId>
      <Id>8</Id>
      <Status>To Do</Status>
    </Entry>
  </Strings>
  <Strings>
    <Section>Unreferenced</Section>
  </Strings>
</SceneText>
