<SceneText>
  <Speakers>
    <Section>Speaker</Section>
    <Entry>
      <JapaneseText>ロイド</JapaneseText>
      <EnglishText/>
      <Notes/>
      <Id>24</Id>
      <Status>To Do</Status>
    </Entry>
    <Entry>
      <JapaneseText>ゼロス</JapaneseText>
      <EnglishText/>
      <Notes/>
      <Id>29</Id>
      <Status>To Do</Status>
    </Entry>
    <Entry>
      <JapaneseText>ナナリー</JapaneseText>
      <EnglishText/>
      <Notes/>
      <Id>21</Id>
      <Status>To Do</Status>
    </Entry>
    <Entry>
      <JapaneseText>ジェイド</JapaneseText>
      <EnglishText/>
      <Notes/>
      <Id>42</Id>
      <Status>To Do</Status>
    </Entry>
  </Speakers>
  <Strings>
    <Section>Main Text</Section>
    <Entry>
      <JapaneseText>よお、ご苦労さん</JapaneseText>
      <EnglishText/>
      <Notes/>
      <SpeakerId>24</SpeakerId>
      <Id>0</Id>
      <Status>To Do</Status>
    </Entry>
    <Entry>
      <JapaneseText>ハニー！
今、戻ったぜぇ〜</JapaneseText>
      <EnglishText/>
      <Notes/>
      <SpeakerId>29</SpeakerId>
      <Id>1</Id>
      <Status>To Do</Status>
    </Entry>
    <Entry>
      <JapaneseText>ああ、なんだか出てったヤツらも
戻ってきたみたいだけどさぁ、
何だかみんな微妙な顔してたね</JapaneseText>
      <EnglishText/>
      <Notes/>
      <SpeakerId>21</SpeakerId>
      <Id>2</Id>
      <Status>To Do</Status>
    </Entry>
    <Entry>
      <JapaneseText>世の中、理不尽で
どうしようもない事もあるという事を
理解してくれたんでしょうね</JapaneseText>
      <EnglishText/>
      <Notes/>
      <SpeakerId>42</SpeakerId>
      <Id>3</Id>
      <Status>To Do</Status>
    </Entry>
    <Entry>
      <JapaneseText>なんだ、そりゃ。
努力して報われない事なんて
間違ってると思うぜ</JapaneseText>
      <EnglishText/>
      <Notes/>
      <SpeakerId>24</SpeakerId>
      <Id>4</Id>
      <Status>To Do</Status>
    </Entry>
    <Entry>
      <JapaneseText>世の中理不尽な事なんてねぇよ！</JapaneseText>
      <EnglishText/>
      <Notes/>
      <SpeakerId>24</SpeakerId>
      <Id>5</Id>
      <Status>To Do</Status>
    </Entry>
    <Entry>
      <JapaneseText>ハニーの言葉は胸に沁みるねえ〜…</JapaneseText>
      <EnglishText/>
      <Notes/>
      <SpeakerId>29</SpeakerId>
      <Id>6</Id>
      <Status>To Do</Status>
    </Entry>
    <Entry>
      <JapaneseText>まったくです</JapaneseText>
      <EnglishText/>
      <Notes/>
      <SpeakerId>42</SpeakerId>
      <Id>7</Id>
      <Status>To Do</Status>
    </Entry>
    <Entry>
      <JapaneseText>だろ？</JapaneseText>
      <EnglishText/>
      <Notes/>
      <SpeakerId>24</SpeakerId>
      <Id>8</Id>
      <Status>To Do</Status>
    </Entry>
    <Entry>
      <JapaneseText>微妙に馬鹿にされてる響きを
感じるんだけど…</JapaneseText>
      <EnglishText/>
      <Notes/>
      <SpeakerId>21</SpeakerId>
      <Id>9</Id>
      <Status>To Do</Status>
    </Entry>
    <Entry>
      <JapaneseText>ん、まあいいか…</JapaneseText>
      <EnglishText/>
      <Notes/>
      <SpeakerId>21</SpeakerId>
      <Id>10</Id>
      <Status>To Do</Status>
    </Entry>
  </Strings>
  <Strings>
    <Section>Unreferenced</Section>
  </Strings>
</SceneText>
