<SceneText>
  <Speakers>
    <Section>Speaker</Section>
    <Entry>
      <PointerOffset/>
      <JapaneseText>パニール</JapaneseText>
      <EnglishText/>
      <Notes/>
      <Id>53</Id>
      <Status>To Do</Status>
    </Entry>
  </Speakers>
  <Strings>
    <Section>Main Text</Section>
    <Entry>
      <PointerOffset/>
      <JapaneseText>マ〜、お疲れ様です。
これでスリムボディになれるのね〜。
ちょっと、おばさんウッキウキよ♪</JapaneseText>
      <EnglishText/>
      <Notes/>
      <SpeakerId>53</SpeakerId>
      <Id>0</Id>
      <Status>To Do</Status>
    </Entry>
    <Entry>
      <PointerOffset/>
      <JapaneseText>それじゃ、○○さん。
ありがとうございました</JapaneseText>
      <EnglishText/>
      <Notes/>
      <SpeakerId>53</SpeakerId>
      <Id>1</Id>
      <Status>To Do</Status>
    </Entry>
    <Entry>
      <PointerOffset/>
      <JapaneseText>私からのお礼、受け取ってくださいね</JapaneseText>
      <EnglishText/>
      <Notes/>
      <SpeakerId>53</SpeakerId>
      <Id>2</Id>
      <Status>To Do</Status>
    </Entry>
  </Strings>
  <Strings>
    <Section>Unreferenced</Section>
  </Strings>
</SceneText>
